Metadata-Version: 1.0
Name: om-probability
Version: 0.1
Summary: Gaussian om_probability
Home-page: UNKNOWN
Author: UNKNOWN
Author-email: UNKNOWN
License: UNKNOWN
Platform: UNKNOWN
